<?xml version="1.0" encoding="UTF-8"?>
<objects serializationModel="Studio.02.02.00">
	<object class="AudioFile" id="{43c0cfa7-382e-4783-b1a7-446bfd3e689f}">
		<property name="assetPath">
			<value>Submarine/AiVoicelines/SafeSurfaceHelmOverride.wav</value>
		</property>
		<property name="frequencyInKHz">
			<value>22.0499992</value>
		</property>
		<property name="channelCount">
			<value>1</value>
		</property>
		<property name="length">
			<value>5.475056689342404</value>
		</property>
		<relationship name="masterAssetFolder">
			<destination>{8baa8edf-b616-4ad9-b2ec-32c7621b7c7c}</destination>
		</relationship>
	</object>
</objects>
